zanj/__init__.py
zanj/externals.py
zanj/loading.py
zanj/py.typed
zanj/serializing.py
zanj/torchutil.py
zanj/zanj.py
zanj-0.5.2.dist-info/METADATA
zanj-0.5.2.dist-info/WHEEL
zanj-0.5.2.dist-info/licenses/LICENSE
zanj-0.5.2.dist-info/RECORD
