Metadata-Version: 2.4
Name: zanj
Version: 0.5.2
Summary: save and load complex objects to disk without pickling
Project-URL: Homepage, https://miv.name/zanj
Project-URL: Repository, https://github.com/mivanit/zanj
Project-URL: Documentation, https://miv.name/zanj/
Project-URL: Issues, https://github.com/mivanit/ZANJ/issues
Author-email: Michael Ivanitskiy <mivanits@umich.edu>
License-Expression: GPL-3.0-only
License-File: LICENSE
Classifier: Development Status :: 4 - Beta
Classifier: License :: OSI Approved :: GNU General Public License v3 (GPLv3)
Classifier: Operating System :: OS Independent
Classifier: Programming Language :: Python :: 3.8
Classifier: Programming Language :: Python :: 3.9
Classifier: Programming Language :: Python :: 3.10
Classifier: Programming Language :: Python :: 3.11
Classifier: Programming Language :: Python :: 3.12
Requires-Python: >=3.8
Requires-Dist: jaxtyping>=0.2.12
Requires-Dist: muutils>=0.8.0
Requires-Dist: numpy>=1.24.4
Provides-Extra: pandas
Requires-Dist: pandas>=1.5.3; extra == 'pandas'
Provides-Extra: torch
Requires-Dist: h11>=0.16.0; extra == 'torch'
Requires-Dist: torch>=1.13.1; extra == 'torch'
